LICENSE.txt
README.md
setup.py
MITuna.egg-info/PKG-INFO
MITuna.egg-info/SOURCES.txt
MITuna.egg-info/dependency_links.txt
MITuna.egg-info/requires.txt
MITuna.egg-info/top_level.txt
flaskapp/__init__.py
flaskapp/app.py
flaskapp/example_app.py
flaskapp/setup.py
tuna/__init__.py
tuna/abort.py
tuna/connection.py
tuna/db_engine.py
tuna/flask.py
tuna/flask_example.py
tuna/go_fish.py
tuna/grafana_dict.py
tuna/lib_utils.py
tuna/libraries.py
tuna/machine.py
tuna/machine_management_interface.py
tuna/mituna_interface.py
tuna/parse_args.py
tuna/session_mixin.py
tuna/sql.py
tuna/tables_interface.py
tuna/worker_interface.py
tuna/yaml_parser.py
tuna/dbBase/__init__.py
tuna/dbBase/base_class.py
tuna/dbBase/sql_alchemy.py
tuna/example/__init__.py
tuna/example/example_lib.py
tuna/example/example_tables.py
tuna/example/example_worker.py
tuna/example/load_job.py
tuna/example/metadata.py
tuna/example/session.py
tuna/example/tables.py
tuna/miopen/__init__.py
tuna/miopen/metadata.py
tuna/miopen/miopen_lib.py
tuna/miopen/parse_miopen_args.py
tuna/utils/__init__.py
tuna/utils/db_utility.py
tuna/utils/logger.py
tuna/utils/miopen_utility.py
tuna/utils/utility.py