Metadata-Version: 2.1
Name: MITuna
Version: 1.0
Summary: Tuna is a distributed tuning infrastructure that provides pre-compiled kernels for MIOpen customers through automated Jenkins pipelines and SLURM scalable architecture. MITuna also provides a scalable task management infrastructure ready to integrate with external libaries.
Home-page: https://github.com/ROCmSoftwarePlatform/MITuna.git
License: MIT
Requires-Python: >=3.9
License-File: LICENSE.txt
